factorial_minh/__init__.py
factorial_minh/app.py
factorial_minh/factorial.py
factorial_minh-0.1.0.dist-info/METADATA
factorial_minh-0.1.0.dist-info/WHEEL
factorial_minh-0.1.0.dist-info/RECORD
