Metadata-Version: 2.1
Name: factorial-minh
Version: 0.1.0
Summary: 
Author: minh190902
Author-email: nguyendangnhatminh8241@gmail.com
Requires-Python: >=3.10,<4.0
Classifier: Programming Language :: Python :: 3
Classifier: Programming Language :: Python :: 3.10
Classifier: Programming Language :: Python :: 3.11
Classifier: Programming Language :: Python :: 3.12
Requires-Dist: streamlit (>=1.32.2,<2.0.0)
